[1,["67GkU5oItAUqrgO3psQZP1@6c48a"],["_textureSource"],["cc.SpriteFrame"],0,[{"name":"1602","rect":{"x":109,"y":97,"width":282,"height":307},"offset":{"x":0,"y":-0.5},"originalSize":{"width":500,"height":500},"rotated":false,"capInsets":[0,0,0,0],"vertices":{"rawPosition":[-141,-153.5,0,141,-153.5,0,-141,153.5,0,141,153.5,0],"indexes":[0,1,2,2,1,3],"uv":[109,403,391,403,109,96,391,96],"nuv":[0.218,0.192,0.782,0.192,0.218,0.806,0.782,0.806],"minPos":{"x":-141,"y":-153.5,"z":0},"maxPos":{"x":141,"y":153.5,"z":0}},"packable":true,"pixelsToUnit":100,"pivot":{"x":0.5,"y":0.5},"meshType":0}],[0],0,[0],[0],[0]]
