[1,["58VbN5vRNJhY5wJAbjDR3Z@6c48a"],["_textureSource"],["cc.SpriteFrame"],0,[{"name":"1901","rect":{"x":161,"y":100,"width":179,"height":301},"offset":{"x":0.5,"y":-0.5},"originalSize":{"width":500,"height":500},"rotated":false,"capInsets":[0,0,0,0],"vertices":{"rawPosition":[-89.5,-150.5,0,89.5,-150.5,0,-89.5,150.5,0,89.5,150.5,0],"indexes":[0,1,2,2,1,3],"uv":[161,400,340,400,161,99,340,99],"nuv":[0.322,0.198,0.68,0.198,0.322,0.8,0.68,0.8],"minPos":{"x":-89.5,"y":-150.5,"z":0},"maxPos":{"x":89.5,"y":150.5,"z":0}},"packable":true,"pixelsToUnit":100,"pivot":{"x":0.5,"y":0.5},"meshType":0}],[0],0,[0],[0],[0]]
